ScrapeData/TableParser.py
ScrapeData/Utils.py
ScrapeData/__init__.py
ScrapeData/example.py
ScrapeData-0.0.6.dist-info/LICENSE.txt
ScrapeData-0.0.6.dist-info/METADATA
ScrapeData-0.0.6.dist-info/WHEEL
ScrapeData-0.0.6.dist-info/top_level.txt
ScrapeData-0.0.6.dist-info/RECORD
