Metadata-Version: 2.1
Name: ScrapeData
Version: 0.0.6
Summary: Python module to get table data from any webpage and converts it into either Json or Csv
Home-page: https://github.com/mk6619/
Author: Mayank khursija
Author-email: mk6619@gmail.com
License: UNKNOWN
Platform: UNKNOWN
Classifier: Programming Language :: Python :: 3
Classifier: License :: OSI Approved :: MIT License
Classifier: Operating System :: OS Independent
Requires-Dist: setuptools
Requires-Dist: pandas
Requires-Dist: requests
Requires-Dist: beautifulsoup4
